my_awesome_library/__init__.py
my_awesome_library/main_module.py
my_awesome_library-0.0.1.dist-info/licenses/LICENSE.txt
my_awesome_library-0.0.1.dist-info/METADATA
my_awesome_library-0.0.1.dist-info/WHEEL
my_awesome_library-0.0.1.dist-info/top_level.txt
my_awesome_library-0.0.1.dist-info/RECORD
